tests/__init__.py
tests/test_config_handler.py
tests/test_diff_handler.py
tests/test_git_handler.py
tests/test_gitlab_handler.py
diffdewind-0.2.0.dist-info/METADATA
diffdewind-0.2.0.dist-info/WHEEL
diffdewind-0.2.0.dist-info/entry_points.txt
diffdewind-0.2.0.dist-info/top_level.txt
diffdewind-0.2.0.dist-info/RECORD
