Metadata-Version: 2.1
Name: diffdewind
Version: 0.2.0
Requires-Dist: requests >=2.26.0
Provides-Extra: dev
Requires-Dist: pytest >=7.1.2 ; extra == 'dev'
